{
    "data": [
        {"ourQualities" : [
            {
                "id": 1,
                "image": "quality",
                "title": "QUALITY FOOD",
                "description": "Lorem ipsum dolor sit amet consectetur adipisicing elit. Officiis repellendus officia qui repellat." 
            },
            {
                "id": 2,
                "image": "fresh",
                "title": "SUPER TASTE",
                "description": "Lorem ipsum dolor sit amet consectetur, adipisicing sit amet elit. Sit voluptates quaerat pariatur." 
            },
            {
                "id": 3,
                "image": "delivery",
                "title": "FAST DELIVERY",
                "description": "Lorem ipsum dolor sit amet consectetur adipisicing elit. Officiis repellendus officia qui repellat." 
            }
        ],
        "dishes": [
            {
                "id": 1,
                "image": "lamb",
                "title": "ROASTED LAMB RUMP",
                "category": "Dinner"
            },
            {
                "id": 2,
                "image": "salmon",
                "title": "CITRUS CURED SALMON",
                "category": "Dinner"
            },
            {
                "id": 3,
                "image": "seabass",
                "title": "PAN SEARED SEA BASS",
                "category": "Breakfast"
            },
            {
                "id": 4,
                "image": "strawberry",
                "title": "STUFFED STRAWBERRY",
                "category": "Dinner"
            },
            {
                "id": 5,
                "image": "burger",
                "title": "BURGER MEAL",
                "category": "Lunch"
            },
            {
                "id": 6,
                "image": "soup",
                "title": "CHICKEN SOUP",
                "category": "Dinner"
            },
            {
                "id": 7,
                "image": "spaghetti",
                "title": "ITALIAN SPAGHETTI",
                "category": "Dinner"
            },
            {
                "id": 8,
                "image": "fish",
                "title": "GRILLED FISH",
                "category": "Dinner"
            }
        ],
        "team": [
            {
                "id": 1,
                "image": "./team_member_1.png",
                "name": "Ravichandran ashwin",
                "designation": "Founder & Head Chef"
            },
            {
                "id": 2,
                "image": "./team_member_2.png",
                "name": "WADE WARREN",
                "designation": "Sous Chef"
            },
            {
                "id": 3,
                "image": "./team_member_3.png",
                "name": "JHON DOE",
                "designation": "Fast Food Chef"
            },
            {
                "id": 4,
                "image": "./team_member_4.png",
                "name": "ALEX COAL",
                "designation": "Senior Chef"
            }
        ],
        "testimonials": [
            {
                "id": 1,
                "image": "./review1.png",
                 "title": "A perfect place for family dinners.",
                "description": "Great ambience, quick service, and dishes that taste as good as they look. We’ll definitely be coming back again.",
                "rating": 4,
                "userName": "Anjali Arora"
            },
            {
                "id": 2,
                "image": "./review2.png",
                "title": "Absolutely loved the experience!",
                "description": "The food was fresh, flavorful, and beautifully presented. The reservation process was smooth, and the staff made us feel truly welcome..",
                "rating": 4.5,
                "userName": "Shreya Thakur"
            },
            {
                "id": 3,
                "image": "./review3.png",
                 "title": "One of the best dining experiences in the city",
                "description": "From the starters to the desserts, everything was top-notch. Booking a table was super easy and hassle-free.",
                "rating": 5,
                "userName": "Amrita Dhattalia"
            }
        ],
        "who_we_are": [
            {
                "id": 1,
                "number": "14",
                "title": "Restaurants"
            },
            {
                "id": 2,
                "number": "20",
                "title": "Chef In Kitchen"
            },
            {
                "id": 3,
                "number": "08",
                "title": "Years Of Experience"
            },
            {
                "id": 4,
                "number": "200",
                "title": "Food Dishes"
            }
        ],
        "navbarLinks": [
            {
                "id": 1,
                "title": "HOME",
                "link": "heroSection"
            },
            {
                "id": 2,
                "title": "ABOUT US",
                "link": "about"
            },
            {
                "id": 3,
                "title": "SERVICES",
                "link": "qualities"
            },
            {
                "id": 5,
                "title": "RESERVATION",
                "link": "reservation"
            }
        ]
    
    } 
    ]
}